Metadata-Version: 1.0
Name: BiGG-SABIO
Version: 0.0.1
Summary: Scrapes SABIO-RK for enzyme kinetics data for given BiGG Model for dFBA simulation.
Home-page: https://github.com/freiburgermsu/BiGG_SABIO
Author: Andrew Freiburger, Ethan Chan
Author-email: andrewfreiburger@gmail.com
License: MIT
Keywords: dFBA,FBA,BiGG,biochemistry,scraping,metabolism,SABIO,SABIO-RK,kinetics,bioinformatics
Platform: UNKNOWN
